LICENSE
MANIFEST.in
README.md
setup.py
footprint_tools/__init__.py
footprint_tools/__main__.py
footprint_tools/cutcounts.py
footprint_tools/logging.conf
footprint_tools.egg-info/PKG-INFO
footprint_tools.egg-info/SOURCES.txt
footprint_tools.egg-info/dependency_links.txt
footprint_tools.egg-info/entry_points.txt
footprint_tools.egg-info/not-zip-safe
footprint_tools.egg-info/requires.txt
footprint_tools.egg-info/top_level.txt
footprint_tools/cli/__init__.py
footprint_tools/cli/autocorr.py
footprint_tools/cli/detect.py
footprint_tools/cli/diff.py
footprint_tools/cli/learn_beta.py
footprint_tools/cli/learn_bm.py
footprint_tools/cli/learn_dm.py
footprint_tools/cli/plot_dm.py
footprint_tools/cli/post.py
footprint_tools/cli/utils.py
footprint_tools/modeling/__init__.py
footprint_tools/modeling/bias.py
footprint_tools/modeling/dispersion.pxd
footprint_tools/modeling/dispersion.pyx
footprint_tools/modeling/predict.h
footprint_tools/modeling/predict.pyx
footprint_tools/modeling/smoothing.h
footprint_tools/plotting/__init__.py
footprint_tools/stats/__init__.py
footprint_tools/stats/differential.pyx
footprint_tools/stats/posterior.py
footprint_tools/stats/utils.pyx
footprint_tools/stats/windowing.h
footprint_tools/stats/windowing.pyx
footprint_tools/stats/distributions/__init__.py
footprint_tools/stats/distributions/invchi2.pxd
footprint_tools/stats/distributions/invchi2.pyx
footprint_tools/stats/distributions/nbinom.pxd
footprint_tools/stats/distributions/nbinom.pyx
footprint_tools/stats/distributions/t.pxd
footprint_tools/stats/distributions/t.pyx
footprint_tools/stats/fdr/__init__.py
hcephes/include/hcephes.h
hcephes/src/mtherr.c
hcephes/src/bessel/airy.c
hcephes/src/bessel/hyp2f1.c
hcephes/src/bessel/hyperg.c
hcephes/src/bessel/i0.c
hcephes/src/bessel/i1.c
hcephes/src/bessel/iv.c
hcephes/src/bessel/j0.c
hcephes/src/bessel/j1.c
hcephes/src/bessel/jn.c
hcephes/src/bessel/jv.c
hcephes/src/bessel/k0.c
hcephes/src/bessel/k1.c
hcephes/src/bessel/kn.c
hcephes/src/bessel/struve.c
hcephes/src/bessel/yn.c
hcephes/src/cmath/cbrt.c
hcephes/src/cmath/powi.c
hcephes/src/cprob/bdtr.c
hcephes/src/cprob/btdtr.c
hcephes/src/cprob/chdtr.c
hcephes/src/cprob/drand.c
hcephes/src/cprob/expx2.c
hcephes/src/cprob/fdtr.c
hcephes/src/cprob/gamma.c
