Metadata-Version: 2.1
Name: footprint-tools
Version: 1.3.7
Summary: Genomic footprint detection
Home-page: https://github.com/jvierstra/footprint-tools
Author: Jeff Vierstra
Author-email: jvierstra@altius.org
License: GPL-3.0-or-later
Download-URL: https://github.com/jvierstra/footprint-tools/archive/v1.3.7.tar.gz
Keywords: genomic footprints,bioinformatics,chromatin,transcription factors,dnase
Platform: UNKNOWN
Classifier: Development Status :: 5 - Production/Stable
Classifier: Intended Audience :: Science/Research
Classifier: Topic :: Scientific/Engineering :: Bio-Informatics
Classifier: License :: OSI Approved :: GNU General Public License v3 or later (GPLv3+)
Classifier: Programming Language :: Python :: 3.6
Classifier: Programming Language :: Python :: 3.7
Classifier: Programming Language :: Python :: 3.8
Classifier: Programming Language :: Python :: 3.9
License-File: LICENSE
